visisipy/__init__.py
visisipy/_zospy_loader.py
visisipy/backend.py
visisipy/plots.py
visisipy/refraction.py
visisipy/types.py
visisipy/wavefront.py
visisipy/analysis/__init__.py
visisipy/analysis/base.py
visisipy/analysis/cardinal_points.py
visisipy/analysis/psf.py
visisipy/analysis/raytracing.py
visisipy/analysis/refraction.py
visisipy/analysis/wavefront.py
visisipy/analysis/zernike_standard_coefficients.py
visisipy/models/__init__.py
visisipy/models/geometry.py
visisipy/models/materials.py
visisipy/opticstudio/__init__.py
visisipy/opticstudio/backend.py
visisipy/opticstudio/models.py
visisipy/opticstudio/surfaces.py
visisipy/opticstudio/analysis/__init__.py
visisipy/opticstudio/analysis/cardinal_points.py
visisipy/opticstudio/analysis/helpers.py
visisipy/opticstudio/analysis/psf.py
visisipy/opticstudio/analysis/raytrace.py
visisipy/opticstudio/analysis/refraction.py
visisipy/opticstudio/analysis/wavefront.py
visisipy/opticstudio/analysis/zernike_coefficients.py
visisipy/optiland/__init__.py
visisipy/optiland/backend.py
visisipy/optiland/models.py
visisipy/optiland/surfaces.py
visisipy/optiland/analysis/__init__.py
visisipy/optiland/analysis/cardinal_points.py
visisipy/optiland/analysis/helpers.py
visisipy/optiland/analysis/psf.py
visisipy/optiland/analysis/raytrace.py
visisipy/optiland/analysis/refraction.py
visisipy/optiland/analysis/wavefront.py
visisipy/optiland/analysis/zernike_coefficients.py
visisipy-0.2.0.dist-info/METADATA
visisipy-0.2.0.dist-info/WHEEL
visisipy-0.2.0.dist-info/licenses/LICENSE.md
visisipy-0.2.0.dist-info/RECORD
