Metadata-Version: 2.4
Name: visisipy
Version: 0.2.0
Summary: Accessible vision simulations in Python.
Author: Corné Haasjes, Jan-Willem Beenakker
Maintainer-email: MReye research group <zospy@mreye.nl>
License-File: LICENSE.md
Requires-Python: <3.14,>=3.10
Requires-Dist: matplotlib
Requires-Dist: numba>=0.60.0
Requires-Dist: numpy
Requires-Dist: optiland>=0.5.6
Requires-Dist: scipy
Requires-Dist: typing-extensions>=4.12.2; python_full_version < '3.11'
Requires-Dist: zospy>=2.1.2; sys_platform == 'win32'
Provides-Extra: torch
Requires-Dist: torch; extra == 'torch'
